[
  {
    "date": "2026-05-23",
    "target_mean": 613.225,
    "buy": 39,
    "hold": 4,
    "sell": 1
  },
  {
    "date": "2026-05-22",
    "target_mean": 613.225,
    "buy": 39,
    "hold": 4,
    "sell": 1
  },
  {
    "date": "2026-05-21",
    "target_mean": 612.65857,
    "buy": 39,
    "hold": 4,
    "sell": 1
  },
  {
    "date": "2026-04-01",
    "target_mean": 723.75,
    "buy": 39,
    "hold": 5,
    "sell": 0
  },
  {
    "date": "2026-03-01",
    "target_mean": 526.21,
    "buy": 38,
    "hold": 5,
    "sell": 0
  },
  {
    "date": "2026-02-01",
    "target_mean": 450.0,
    "buy": 38,
    "hold": 3,
    "sell": 2
  }
]